[
  {
    "name":"页面管理",
    "class":"fa fa-files-o",
    "collapse":true,
    "menuItem":[
      {"name":"网站首页管理","link":"/admin/home-page-admin","class":"fa fa-home"},
      {"name":"组装页面","link":"/admin/pageComponent/build-page","class":"fa fa-home"}
    ]
  },
  {
    "name":"文章管理",
    "class":"fa fa-newspaper-o",
    "collapse":true,
    "menuItem":[
      {"name":"编写文章","link":"/admin/file-editor","class":"fa fa-cog"},
      {"name":"修改文章","link":"/admin/article/list","class":"fa fa-cog"}]
  },
  {
    "name":"全局配置",
    "class":"fa fa-wrench",
    "collapse":true,
    "menuItem":[
      {"name":"aaa","link":"/admin/abc","class":"fa fa-cog"},
      {"name":"aaaa","link":"/admin/abc","class":"fa fa-cog"},
      {"name":"aaaaba","link":"/admin/abc","class":"fa fa-cog"}]
  },
  {
    "name":"关于本系统",
    "class":"fa fa-wrench",
    "collapse":true
  }
]